reqboost.cpython-312-darwin.so
bindings/ApiBindings.cpp
bindings/ExceptionBindings.cpp
bindings/ModelsBindings.cpp
bindings/SessionBindings.cpp
bindings/UtilityBindings.cpp
reqboost-0.0.5.dist-info/LICENSE
reqboost-0.0.5.dist-info/METADATA
reqboost-0.0.5.dist-info/WHEEL
reqboost-0.0.5.dist-info/top_level.txt
reqboost-0.0.5.dist-info/RECORD
