Metadata-Version: 2.1
Name: reqboost
Version: 0.0.5
Summary: Python package for HTTP requests based on C++ libcurl and Poco
Home-page: https://github.com/Khushiyant/reqboost
Author: Khushiyant
Author-email: Khushiyant <khushiyant2002@gmail.com>
License: 
Keywords: python,http,requests,curl,poco,pybind11
Classifier: Programming Language :: Python :: 3
Classifier: Programming Language :: C++
Classifier: Topic :: Internet :: WWW/HTTP
Classifier: License :: OSI Approved :: Apache Software License
Requires-Python: >=3.10
License-File: LICENSE
Requires-Dist: pybind11>=2.10.0
Requires-Dist: cmake
Provides-Extra: test
Requires-Dist: pre-commit; extra == "test"
Requires-Dist: pytest; extra == "test"
